sqlite_orm/__init__.py
sqlite_orm/base.py
sqlite_orm/columns.py
sqlite_orm/helpers.py
sqlite_orm/models.py
sqlite_orm/files/__init__.py
sqlite_orm/files/storage.py
sqlite3_orm-1.0.0.dist-info/LICENSE
sqlite3_orm-1.0.0.dist-info/METADATA
sqlite3_orm-1.0.0.dist-info/WHEEL
sqlite3_orm-1.0.0.dist-info/top_level.txt
sqlite3_orm-1.0.0.dist-info/RECORD
