Metadata-Version: 2.1
Name: sqlite3-orm
Version: 1.0.0
Summary: Django style ORM for sqlite3
Author-email: Thraize <gamerxville@gmail.com>
License: Copyright © 2024 Thraize
Project-URL: Homepage, https://github.com/7HR4IZ3/Sqlite-ORM
Keywords: database,sqlite,orm
Classifier: License :: OSI Approved :: MIT License
Classifier: Programming Language :: Python
Classifier: Programming Language :: Python :: 3
Requires-Python: >=3.6
License-File: LICENSE
Requires-Dist: bottle
Requires-Dist: tomli ; python_version < "3.12"
